{
    "accumulo": "2019-08-13T18:30:06",
    "alacarte": "2019-09-11T09:17:17",
    "audio-convert-mod": "2019-09-11T09:17:19",
    "batti": "2019-09-11T09:17:20",
    "bzr": "2019-09-30T12:06:41",
    "cassandra": "2019-09-17T16:17:39",
    "castor-maven-plugin": "2019-09-26T15:59:28",
    "cbi-plugins": "2019-09-23T12:54:57",
    "chm2pdf": "2019-09-11T09:17:22",
    "concurrentunit": "2019-09-08T19:02:22",
    "diffuse": "2019-10-03T09:55:09",
    "eclipse-dtp": "2019-09-23T12:56:59",
    "eclipse-ecf": "2019-09-23T12:58:31",
    "eclipse-eclemma": "2019-09-23T13:01:19",
    "eclipse-egit-github": "2019-09-23T13:03:04",
    "eclipse-linuxtools": "2019-09-23T13:04:36",
    "eclipse-moreunit": "2019-09-23T13:09:17",
    "eclipse-mpc": "2019-09-23T13:14:10",
    "eclipse-mylyn": "2019-09-23T13:12:50",
    "eclipse-packagekit": "2019-09-23T13:16:55",
    "eclipse-pydev": "2019-09-23T13:15:24",
    "eclipse-swtbot": "2019-09-23T12:52:35",
    "eclipse-tm-terminal": "2019-09-23T12:49:59",
    "euca2ools": "2019-09-11T09:17:23",
    "freemedforms": "2019-09-23T11:53:53",
    "func": "2019-09-11T09:17:27",
    "gcc-python-plugin": "2019-09-13T21:09:39",
    "ginfo": "2019-09-11T09:17:28",
    "git-remote-bzr": "2019-09-18T12:39:12",
    "gnome-python2-extras": "2019-09-11T09:17:31",
    "gnu-regexp": "2019-09-26T16:03:55",
    "gstreamer-python": "2019-09-11T09:17:32",
    "java-base64": "2019-09-23T12:37:04",
    "jenkins": "2019-08-30T06:12:34",
    "jenkins-xstream": "2019-08-30T06:25:14",
    "jetty-version-maven-plugin": "2019-09-23T12:34:43",
    "jetty8": "2019-08-27T09:58:11",
    "js-excanvas": "2019-09-30T12:23:16",
    "jsch-agent-proxy": "2019-09-01T17:25:21",
    "json_diff": "2019-10-04T12:24:33",
    "jthread": "2019-09-06T20:48:46",
    "laditools": "2019-09-11T09:17:33",
    "leafnode": "2019-10-04T12:21:50",
    "libfixposix": "2019-09-30T07:01:42",
    "libodb-boost": "2019-10-08T14:58:29",
    "libodb-qt": "2019-10-08T14:59:51",
    "menulibre": "2019-10-11T14:16:45",
    "mkelfimage": "2019-09-22T06:46:45",
    "nfspy": "2019-10-09T13:48:51",
    "nodejs-flot": "2019-09-30T12:23:51",
    "notify-python": "2019-09-25T14:06:48",
    "openxcap": "2019-09-11T09:17:34",
    "pdf-renderer": "2019-09-15T12:13:19",
    "pegdown": "2019-09-29T12:39:14",
    "pycdio": "2019-09-08T18:35:29",
    "pyftpdlib": "2019-09-15T01:00:33",
    "pypoppler": "2019-10-09T13:48:56",
    "python-application": "2019-09-08T18:35:31",
    "python-arc": "2019-10-10T10:41:38",
    "python-backports-ssl_match_hostname": "2019-09-11T09:17:37",
    "python-cassandra-driver": "2019-09-19T07:56:30",
    "python-chm": "2019-09-11T09:17:38",
    "python-epdb": "2019-09-13T21:09:40",
    "python-gnutls": "2019-09-08T18:35:32",
    "python-jenkinsapi": "2019-09-13T21:09:42",
    "python-ngram": "2019-09-13T21:09:46",
    "python-openid": "2019-09-11T09:17:41",
    "python-progressbar": "2019-09-11T09:17:42",
    "python-pybloomfiltermmap": "2019-09-15T01:06:35",
    "python-qpid": "2019-09-11T09:17:43",
    "python-tbgrep": "2019-09-13T21:09:50",
    "python-tpg": "2019-09-13T21:09:52",
    "python-unittest2": "2019-10-03T14:28:30",
    "python2-typing": "2019-09-11T09:17:44",
    "qpid-cpp": "2019-09-11T09:17:46",
    "radiotray": "2019-09-11T09:17:47",
    "slrn": "2019-10-04T12:24:07",
    "sshj": "2019-09-01T12:37:08",
    "stringtemplate4": "2019-09-23T12:32:54",
    "subdownloader": "2019-09-10T16:50:53",
    "system-config-httpd": "2019-10-03T09:55:06",
    "tagsoup": "2019-09-23T12:40:00",
    "virtio-forwarder": "2019-10-10T10:41:50",
    "wammu": "2019-09-18T10:54:00",
    "winswitch": "2019-09-11T09:17:48",
    "wraplinux": "2019-09-22T06:47:30",
    "xom": "2019-08-27T09:58:21",
    "yaws": "2019-10-10T10:42:00",
    "zynjacku": "2019-09-11T09:17:49"
}